root_mcp/__init__.py
root_mcp/config.py
root_mcp/server.py
root_mcp/common/__init__.py
root_mcp/common/cache.py
root_mcp/common/errors.py
root_mcp/common/utils.py
root_mcp/core/__init__.py
root_mcp/core/io/__init__.py
root_mcp/core/io/exporters.py
root_mcp/core/io/file_manager.py
root_mcp/core/io/readers.py
root_mcp/core/io/validators.py
root_mcp/core/operations/__init__.py
root_mcp/core/operations/basic_stats.py
root_mcp/core/tools/__init__.py
root_mcp/core/tools/data_access.py
root_mcp/core/tools/discovery.py
root_mcp/extended/__init__.py
root_mcp/extended/analysis/__init__.py
root_mcp/extended/analysis/correlations.py
root_mcp/extended/analysis/expression.py
root_mcp/extended/analysis/fitting.py
root_mcp/extended/analysis/histograms.py
root_mcp/extended/analysis/kinematics.py
root_mcp/extended/analysis/operations.py
root_mcp/extended/analysis/plotting.py
root_mcp/extended/tools/__init__.py
root_mcp/extended/tools/analysis.py
root_mcp/extended/tools/plotting.py
root_mcp-0.1.4.dist-info/licenses/LICENSE
root_mcp-0.1.4.dist-info/METADATA
root_mcp-0.1.4.dist-info/WHEEL
root_mcp-0.1.4.dist-info/entry_points.txt
root_mcp-0.1.4.dist-info/top_level.txt
root_mcp-0.1.4.dist-info/RECORD
