Metadata-Version: 2.4
Name: root-mcp
Version: 0.1.4
Summary: Production-grade MCP server for CERN ROOT file analysis
Author: Mohamed Elashri
Maintainer: Mohamed Elashri
License: MIT License
Project-URL: Homepage, https://github.com/MohamedElashri/root-mcp
Project-URL: Repository, https://github.com/MohamedElashri/root-mcp
Project-URL: Issues, https://github.com/MohamedElashri/root-mcp/issues
Project-URL: Documentation, https://github.com/MohamedElashri/root-mcp/tree/main/docs
Project-URL: Changelog, https://github.com/MohamedElashri/root-mcp/blob/main/CHANGELOG.md
Keywords: ROOT,CERN,HEP,MCP,particle physics
Classifier: Development Status :: 4 - Beta
Classifier: Intended Audience :: Science/Research
Classifier: License :: OSI Approved :: MIT License
Classifier: Programming Language :: Python :: 3.10
Classifier: Programming Language :: Python :: 3.11
Classifier: Programming Language :: Python :: 3.12
Classifier: Programming Language :: Python :: 3.13
Classifier: Programming Language :: Python :: 3.14
Classifier: Topic :: Scientific/Engineering :: Physics
Requires-Python: >=3.10
License-File: LICENSE
Requires-Dist: uproot<6.0.0,>=5.0.0
Requires-Dist: awkward<3.0.0,>=2.0.0
Requires-Dist: numpy<2.0.0,>=1.24.0
Requires-Dist: pandas<3.0.0,>=2.0.0
Requires-Dist: mcp>=0.9.0
Requires-Dist: pydantic<3.0.0,>=2.0.0
Requires-Dist: pydantic-settings>=2.0.0
Requires-Dist: aiofiles>=23.0.0
Requires-Dist: fsspec>=2023.0.0
Requires-Dist: pyarrow>=14.0.0
Requires-Dist: pyyaml>=6.0
Requires-Dist: xxhash>=3.0.0
Requires-Dist: scipy>=1.10.0
Requires-Dist: matplotlib>=3.7.0
Provides-Extra: dev
Requires-Dist: pytest>=7.0.0; extra == "dev"
Requires-Dist: pytest-asyncio>=0.21.0; extra == "dev"
Requires-Dist: pytest-cov>=4.0.0; extra == "dev"
Requires-Dist: black>=23.0.0; extra == "dev"
Requires-Dist: ruff>=0.1.0; extra == "dev"
Requires-Dist: ty>=0.0.2; extra == "dev"
Requires-Dist: types-PyYAML>=6.0.0.0; extra == "dev"
Requires-Dist: pre-commit>=3.0.0; extra == "dev"
Requires-Dist: build>=1.0.0; extra == "dev"
Requires-Dist: twine>=4.0.0; extra == "dev"
Provides-Extra: xrootd
Requires-Dist: XRootD>=5.5.0; extra == "xrootd"
Dynamic: license-file
